Workbook

Sheet 1_Resumo_Info
A1: Pergunta | B1: Resposta do Cliente
A2: Nome da Empresa | B2: MaxDistribuidora
A3: Segmento / Nicho | B3: Distribuição de bebidas
A4: Cidade / Região de Atuação | B4: Porto
A5: Tempo de Mercado (anos) | B5: 12
A6: Faturamento Mensal Médio (€) | B6: ='7_Margem_Markup'!B4 -> 90000
A7: Faturamento Anual Estimado (€) | B7: =B6*12 -> 1080000
A8: Ticket Médio (€) | B8: ='6_Ticket_Medio'!D6 -> 160.31746
A9: Margem Bruta (%) | B9: ='7_Margem_Markup'!B7 -> 17.666667
A10: Markup (%) | B10: ='7_Margem_Markup'!B8 -> 1.2145749
A11: Custo Fixo Mensal (€) | B11: ='8_Custos_Estoque'!B7 -> 32000
A12: Custo Variável Médio Mensal (€) | B12: ='8_Custos_Estoque'!B13 -> 22000
A13: Número de Funcionários | B13: 14
A14: Estoque Médio Mensal (€) | B14: ='8_Custos_Estoque'!B18 -> 35000
A15: Percentual de Clientes Recorrentes (%) | B15: ='9_Clientes_Conversao_CAC'!B9 -> 20
A16: Taxa de Conversão (Leads → Vendas) (%) | B16: ='9_Clientes_Conversao_CAC'!B6 -> 10
A17: CAC Atual (Custo para adquirir 1 cliente) (€) | B17: ='9_Clientes_Conversao_CAC'!B5 -> 37.5
A18: Percentual de Vendas Online (%) | B18: ='10_Canais_Venda'!C2 -> 15.789474
A19: Percentual de Vendas Presenciais (%) | B19: ='10_Canais_Venda'!C3 -> 73.684211
A20: Investimento Atual em Marketing (€ / mês) | B20: ='9_Clientes_Conversao_CAC'!B3 -> 80
A21: Meta de Crescimento em 12 meses (%) | B21: ='11_Crescimento_Caixa_Dividas'!B5 -> 20
A22: Situação de Caixa (Sobra, Equilíbrio, Aperto) | B22: ='11_Crescimento_Caixa_Dividas'!B9 -> Aperto
A23: Dívidas / Financiamentos Relevantes (€) | B23: ='11_Crescimento_Caixa_Dividas'!B8 -> 25000
A24: Índice de Penetração no Mercado (Baixo / Médio / Alto) | B24: ='12_Penetracao_Mercado'!B5 -> Baixo
A25: Principais Concorrentes | B25: 5 distribuidores grandes
A26: Principais Canais de Venda Hoje | B26: Vendedor externo, WhatsApp, telefone
A27: Principais Desafios Percebidos pelo Dono | B27: Baixa margem, alta concorrência

Sheet 2_Analise_Fin
A1: Indicador | B1: Descrição / Observação | C1: Valor / Cálculo
A2: Faturamento Mensal Médio (€) | B2: Puxado automaticamente da aba 1 (Resumo) | C2: ='1_Resumo_Info'!B6 -> 90000
A3: Margem Bruta (%) | B3: Puxado automaticamente da aba 1 (Resumo) | C3: ='1_Resumo_Info'!B9 -> 17.666667
A4: Lucro Bruto Mensal (€) | B4: Cálculo: Faturamento x Margem | C4: =C2*(C3/100) -> 15900
A5: Custo Fixo Mensal (€) | B5: Puxado automaticamente da aba 1 (Resumo) | C5: ='1_Resumo_Info'!B10 -> 1.2145749
A6: Lucro Operacional Estimado (€) | B6: Cálculo: Lucro bruto - custo fixo | C6: =C4-C5 -> 15898.785
A7: Ponto de Equilíbrio (estimado) (€) | B7: Cálculo: custo fixo dividido pela margem | C7: =IF(C3>0,C5/(C3/100),0) -> 6.8749523
A8: Investimento Seguro em Marketing (3% faturamento) (€) | B8: 3% do faturamento mensal | C8: =C2*0.03 -> 2700
A9: Investimento Moderado em Marketing (5% faturamento) (€) | B9: 5% do faturamento mensal | C9: =C2*0.05 -> 4500
A10: Investimento Agressivo em Marketing (10% faturamento) (€) | B10: 10% do faturamento mensal | C10: =C2*0.1 -> 9000
A11: Grau de Risco (Baixo / Médio / Alto) | B11: Definido automaticamente pela relação lucro x faturamento | C11: =IF(C6<=0,"Alto",IF(C6<C2*0.1,"Médio","Baixo")) -> Baixo
A12: CAC Máximo Recomendado (€) | B12: 20% do ticket médio (aba 1) | C12: ='1_Resumo_Info'!B8*0.2 -> 32.063492
A13: Custo Máximo por Lead Recomendado (€) | B13: 5% do ticket médio (aba 1) | C13: ='1_Resumo_Info'!B8*0.05 -> 8.015873

Sheet 3_Perfil_Crescimento
A1: Critério | B1: Avaliação (Baixo / Médio / Alto ou Descrição) | C1: Comentário Estratégico
A2: Situação de Caixa | B2: =IF('2_Analise_Fin'!C6<=0,"Baixa",IF('2_Analise_Fin'!C6<'2_Analise_Fin'!C2*0.1,"Equilíbrio","Alta")) -> Alta | C2: Baseado na relação entre lucro operacional e faturamento.
A3: Margem Bruta (%) | B3: =IF('2_Analise_Fin'!C3<20,"Baixa",IF('2_Analise_Fin'!C3<40,"Equilíbrio","Alta")) -> Baixa | C3: Classificação automática com base na margem bruta calculada.
A4: Crescimento de Faturamento nos últimos 12 meses | B4: =IF('11_Crescimento_Caixa_Dividas'!B4<10,"Baixa",IF('11_Crescimento_Caixa_Dividas'!B4<25,"Equilíbrio","Alta")) -> Equilíbrio | C4: Usa a meta/resultado de crescimento em 12 meses.
A5: Capacidade de Investimento em Marketing | B5: =IF('2_Analise_Fin'!C11="Alto","Baixa",IF('2_Analise_Fin'!C11="Médio","Limitada","Alta")) -> Alta | C5: Compara investimento recomendado com capacidade de lucro.
A6: Organização de Processos Comerciais | B6: =IF('2_Analise_Fin'!C10="Alto","Baixa",IF('2_Analise_Fin'!C10="Médio","Limitada","Alta")) -> Alta | C6: Usa o grau de risco como proxy da organização interna.
A7: Nível de Concorrência no Nicho | B7: =IF('12_Penetracao_Mercado'!B5="Alto","Alta",IF('12_Penetracao_Mercado'!B5="Médio","Equilíbrio","Baixa")) -> Baixa | C7: Reflete o quão saturado é o mercado em que a empresa atua.

Sheet 4_Recomendacao
A1: Pacote | B1: Orçamento Indicativo (€ / mês) | C1: Perfil de Empresa Ideal | D1: Observações / Ajustes para o Cliente
A2: Starter | B2: Até 500€ | C2: =IF('2_Analise_Fin'!C2<=30000,"Micro/pequena, começando no digital, pouco histórico de marketing","") | D2: =IF(C2<>"","Ideal para testar o canal digital com risco controlado.","")
A3: Intermediário | B3: 500€ - 1.500€ | C3: =IF(AND('2_Analise_Fin'!C2>30000,'2_Analise_Fin'!C2<=80000),"Negócio já validado, quer organizar e crescer com previsibilidade","") | D3: =IF(C3<>"","Equilíbrio entre investimento e retorno esperado.","")
A4: Expansão | B4: 1.500€ - 3.000€ | C4: =IF(AND('2_Analise_Fin'!C2>80000,'2_Analise_Fin'!C2<=150000),"Empresa em expansão com boa margem, quer dominar o nicho","") -> Empresa em expansão com boa margem, quer dominar o nicho | D4: =IF(C4<>"","Recomendado se houver apetite para crescer e capacidade operacional para suportar o volume.","") -> Recomendado se houver apetite para crescer e capacidade operacional para suportar o volume.
A5: Operação Total | B5: Acima de 3.000€ | C5: =IF('2_Analise_Fin'!C2>150000,"Empresa estruturada, foco em escala, múltiplos canais e automação","") | D5: =IF(C5<>"","Indicado para empresas que já dominam processos internos e querem escalar.","")

Sheet 5_Relatorio
A1: Campo | B1: Conteúdo para Preenchimento / Apresentação ao Cliente
A2: Resumo da Situação Atual da Empresa | B2: ="A empresa "&'1_Resumo_Info'!B2&" atua no segmento de "&'1_Resumo_Info'!B3&" na região de "&'1_Resumo_Info'!B4&", com faturamento médio mensal de "&TEXT('1_Resumo_Info'!B6,"#,##0")&"€ e margem bruta de "&TEXT('1_Resumo_Info'!B9,"0")&"%." -> A empresa MaxDistribuidora atua no segmento de Distribuição de bebidas na região de Porto, com faturamento médio mensal de 90 000€ e margem bruta de 18%.
A3: Pontos Fortes | B3: ="Histórico de "&'1_Resumo_Info'!B4&" anos de atuação, carteira consolidada e faturamento recorrente." -> Histórico de Porto anos de atuação, carteira consolidada e faturamento recorrente.
A4: Principais Riscos / Fragilidades | B4: ="Margem bruta de "&TEXT('2_Analise_Fin'!C3,"0")&"% em um mercado competitivo exige disciplina de preço e volume, com atenção à concorrência (percepção: "&'1_Resumo_Info'!B23&")." -> Margem bruta de 18% em um mercado competitivo exige disciplina de preço e volume, com atenção à concorrência (percepção: 25000).
A5: Potencial de Crescimento | B5: ="Com meta de crescimento de "&TEXT('11_Crescimento_Caixa_Dividas'!B5,"0")&"% em 12 meses, há potencial de crescimento compatível com o setor, desde que o investimento em marketing seja alinhado à capacidade de caixa e margem." -> Com meta de crescimento de 20% em 12 meses, há potencial de crescimento compatível com o setor, desde que o investimento em marketing seja alinhado à capacidade de caixa e margem.
A6: Investimento em Marketing Recomendado (Faixa) | B6: ="Com base no faturamento atual, o investimento recomendado em marketing fica entre "&TEXT('2_Analise_Fin'!C8,"#,##0")&"€ e "&TEXT('2_Analise_Fin'!C9,"#,##0")&"€ por mês." -> Com base no faturamento atual, o investimento recomendado em marketing fica entre 2 700€ e 4 500€ por mês.
A7: Justificativa Técnica para o Investimento | B7: ="Os percentuais de 3% a 5% do faturamento consideram a realidade de margem e risco calculados na análise financeira, permitindo testar, otimizar e só então ganhar escala com segurança." -> Os percentuais de 3% a 5% do faturamento consideram a realidade de margem e risco calculados na análise financeira, permitindo testar, otimizar e só então ganhar escala com segurança.
A8: Próximos Passos Sugeridos (em 90 dias) | B8: ="1) Organizar funil comercial e CRM. 2) Estruturar campanhas focadas em clientes de maior volume. 3) Acompanhar KPIs como ticket médio, margem, CAC e churn mensalmente." -> 1) Organizar funil comercial e CRM. 2) Estruturar campanhas focadas em clientes de maior volume. 3) Acompanhar KPIs como ticket médio, margem, CAC e churn mensalmente.

Sheet 6_Ticket_Medio
A1: Canal | B1: Nº de Vendas no Período | C1: Faturamento no Período (€) | D1: Ticket Médio (€)
A2: Vendedor Externo | B2: 320 | C2: 58000 | D2: =IF(B2>0,C2/B2,"") -> 181.25
A3: WhatsApp | B3: 180 | C3: 24000 | D3: =IF(B3>0,C3/B3,"") -> 133.33333
A4: Telefone | B4: 90 | C4: 14000 | D4: =IF(B4>0,C4/B4,"") -> 155.55556
A5: Outros | B5: 40 | C5: 5000 | D5: =IF(B5>0,C5/B5,"") -> 125
A6: TOTAL | B6: =SUM(B2:B5) -> 630 | C6: =SUM(C2:C5) -> 101000 | D6: =IF(B6>0,C6/B6,"") -> 160.31746

Sheet 7_Margem_Markup
A1: Descrição | B1: Valor (€)
A2: Receita Bruta de Vendas (mensal) | B2: 95000
A3: Devoluções / Descontos | B3: 5000
A4: Receita Líquida de Vendas (mensal) | B4: =B2-B3 -> 90000
A5: Custo dos Produtos Vendidos (CPV) | B5: 74100
A6: Lucro Bruto | B6: =B4-B5 -> 15900
A7: Margem Bruta (%) | B7: =IF(B4>0,B6/B4*100,"") -> 17.666667
A8: Markup (Receita Líquida / CPV) | B8: =IF(B5>0,B4/B5,"") -> 1.2145749

Sheet 8_Custos_Estoque
A1: Descrição | B1: Valor (€)
A2: Aluguel | B2: 8000
A3: Salários administrativos | B3: 18000
A4: Contabilidade e serviços | B4: 2000
A5: Energia / Água / Internet | B5: 1500
A6: Outros custos fixos | B6: 2500
A7: TOTAL CUSTO FIXO MENSAL | B7: =SUM(B2:B6) -> 32000
A9: Comissões de venda | B9: 12000
A10: Fretes | B10: 6000
A11: Impostos sobre vendas (variáveis) | B11: 4000
A12: Outros custos variáveis | B12: 0
A13: TOTAL CUSTO VARIÁVEL MENSAL | B13: =SUM(B8:B11) -> 22000
A15: Estoque mês -2 | B15: 34000
A16: Estoque mês -1 | B16: 36000
A17: Estoque mês atual | B17: 35000
A18: Estoque médio dos últimos 3 meses (€) | B18: =AVERAGE(B14:B16) -> 35000

Sheet 9_Clientes_Conversao_CAC
A1: Indicador | B1: Valor
A2: Leads no período (ex: 30 dias) | B2: 800
A3: Vendas no período | B3: 80
A4: Investimento em marketing no período (€) | B4: 3000
A5: CAC (Investimento / Vendas) (€) | B5: =IF(B3>0,B4/B3,"") -> 37.5
A6: Taxa de Conversão (Vendas / Leads) (%) | B6: =IF(B2>0,B3/B2*100,"") -> 10
A7: Clientes recorrentes no período | B7: 50
A8: Total de clientes ativos | B8: 200
A9: % Clientes Recorrentes (%) | B9: =IF(B7>0,B6/B7*100,"") -> 20

Sheet 10_Canais_Venda
A1: Canal | B1: Faturamento (€) | C1: % do Total
A2: Online (site, e-commerce, pedidos digitais) | B2: 15000 | C2: =IF($B$5>0,B2/$B$5*100,"") -> 15.789474
A3: Presencial (loja física, balcão) | B3: 70000 | C3: =IF($B$5>0,B3/$B$5*100,"") -> 73.684211
A4: Outros canais | B4: 10000 | C4: =IF($B$5>0,B4/$B$5*100,"") -> 10.526316
A5: TOTAL | B5: =SUM(B2:B4) -> 95000

Sheet 11_Crescimento_Caixa_Dividas
A1: Indicador | B1: Valor
A2: Faturamento há 12 meses (€) | B2: 80000
A3: Faturamento atual (€) | B3: ='1_Resumo_Info'!B6 -> 90000
A4: Crescimento realizado em 12 meses (%) | B4: =IF(B2>0,B3/B2*100-100,"") -> 12.5
A5: Meta de Crescimento em 12 meses (%) | B5: 20
A6: Saldo médio de caixa mensal (€) | B6: 15000
A7: Média de saídas mensais (€) | B7: 14000
A8: Dívidas / Financiamentos Relevantes (€) | B8: 25000
A9: Situação de Caixa (texto) | B9: =IF(B5>B6,"Sobra",IF(B5>=B6*0.9,"Equilíbrio","Aperto")) -> Aperto

Sheet 12_Penetracao_Mercado
A1: Indicador | B1: Valor
A2: Nº de clientes ativos | B2: ='9_Clientes_Conversao_CAC'!B7 -> 50
A3: Nº estimado de clientes potenciais no mercado | B3: 1500
A4: Participação aproximada (%) | B4: =IF(B3>0, B2/B3 * 100, "") -> 3.3333333
A5: Classificação de Penetração (Baixo / Médio / Alto) | B5: =IF(B4<10,"Baixo",IF(B4<30,"Médio","Alto")) -> Baixo
